AUTHORS.rst
CONTRIBUTING.rst
HISTORY.rst
LICENSE
MANIFEST.in
README.rst
pyproject.toml
setup.cfg
setup.py
docs/Makefile
docs/authors.rst
docs/conf.py
docs/contributing.rst
docs/history.rst
docs/index.rst
docs/installation.rst
docs/make.bat
docs/readme.rst
docs/usage.rst
tests/__init__.py
tests/test_treasureguarder.py
treasure_guarder.egg-info/PKG-INFO
treasure_guarder.egg-info/SOURCES.txt
treasure_guarder.egg-info/dependency_links.txt
treasure_guarder.egg-info/entry_points.txt
treasure_guarder.egg-info/not-zip-safe
treasure_guarder.egg-info/requires.txt
treasure_guarder.egg-info/top_level.txt
treasureguarder/__init__.py
treasureguarder/__main__.py
treasureguarder/treasureguarder.py