Metadata-Version: 1.1
Name: treasure-guarder
Version: 0.0.3
Summary: A python script for backup repositories to custom git server
Home-page: https://github.com/starofrainnight/treasure-guarder
Author: Hong-She Liang
Author-email: starofrainnight@gmail.com
License: Apache Software License
Keywords: treasureguarder,treasure-guarder
Platform: UNKNOWN
Classifier: Development Status :: 2 - Pre-Alpha
Classifier: Intended Audience :: Developers
Classifier: License :: OSI Approved :: Apache Software License
Classifier: Programming Language :: Python :: 3
Classifier: Programming Language :: Python :: 3.5
Classifier: Programming Language :: Python :: 3.6
Classifier: Programming Language :: Python :: 3.7
